odoo/addons/purchase_order_line_display_number/README.rst
odoo/addons/purchase_order_line_display_number/__manifest__.py
odoo/addons/purchase_order_line_display_number/data/purchase_order_line_display_number_data.xml
odoo/addons/purchase_order_line_display_number/static/description/icon.png
odoo/addons/purchase_order_line_display_number/static/src/js/form_view.js
odoo_addon_purchase_order_line_display_number-15.0.1.0.0.1.dist-info/METADATA
odoo_addon_purchase_order_line_display_number-15.0.1.0.0.1.dist-info/WHEEL
odoo_addon_purchase_order_line_display_number-15.0.1.0.0.1.dist-info/top_level.txt
odoo_addon_purchase_order_line_display_number-15.0.1.0.0.1.dist-info/RECORD
